pyapollos/__init__.py
xtPyapollos-0.0.2.dist-info/METADATA
xtPyapollos-0.0.2.dist-info/WHEEL
xtPyapollos-0.0.2.dist-info/top_level.txt
xtPyapollos-0.0.2.dist-info/RECORD
