Metadata-Version: 2.1
Name: xtPyapollos
Version: 0.0.2
Summary: UNKNOWN
Home-page: UNKNOWN
Author: Maoxinteng
Author-email: 1214403402@qq.com
License: UNKNOWN
Platform: UNKNOWN
Classifier: Programming Language :: Python :: 3.6
Classifier: License :: OSI Approved :: MIT License
Classifier: Operating System :: OS Independent
Requires-Python: >=3.6
Requires-Dist: pyapollos (>=0.1.5)
